LICENSE
MANIFEST.in
README.md
setup.py
pipping_easy_install.egg-info/PKG-INFO
pipping_easy_install.egg-info/SOURCES.txt
pipping_easy_install.egg-info/dependency_links.txt
pipping_easy_install.egg-info/entry_points.txt
pipping_easy_install.egg-info/not-zip-safe
pipping_easy_install.egg-info/pbr.json
pipping_easy_install.egg-info/requires.txt
pipping_easy_install.egg-info/top_level.txt
pippingeasyinstall/Downloader.py
pippingeasyinstall/Installer.py
pippingeasyinstall/PackageStore.py
pippingeasyinstall/RegisterPy.py
pippingeasyinstall/__init__.py