Metadata-Version: 1.1
Name: pipping-easy-install
Version: 0.5.0
Summary: Installs Python win32 executable installers using pywinauto.
Home-page: https://github.com/st-james-software/pipping-easy-install
Author: Matthew Hampton
Author-email: support@j5int.com
License: Apache License, Version 2.0
Keywords: easy_install pip windows
Platform: UNKNOWN
Classifier: Development Status :: 3 - Alpha
Classifier: Intended Audience :: Developers
Classifier: License :: OSI Approved :: Apache Software License
Classifier: Operating System :: Microsoft :: Windows
Classifier: Topic :: Software Development :: Libraries
Classifier: Topic :: Software Development :: Libraries :: Python Modules
Classifier: Programming Language :: Python
Classifier: Programming Language :: Python :: 2 :: Only
